asyffmpeg/__init__.py
asyffmpeg/statistic.py
asyffmpeg/tempf.py
asyffmpeg/util.py
asyffmpeg-0.2.4.dist-info/METADATA
asyffmpeg-0.2.4.dist-info/WHEEL
asyffmpeg-0.2.4.dist-info/top_level.txt
asyffmpeg-0.2.4.dist-info/RECORD
