Metadata-Version: 2.1
Name: asyffmpeg
Version: 0.2.4
Summary: A library for asynchronous operation with FFmpeg, providing the ability to track events such as start, end, and encoding progress.
Home-page: https://github.com/drhspfn/asyffmpeg
Author: drhspfn
Author-email: jenya.gsta@gmail.com
Classifier: Programming Language :: Python :: 3
Requires-Dist: aiofiles
Requires-Dist: ffprobe-python
